htmlwebshot/__init__.py
htmlwebshot/config.py
htmlwebshot/shotter.py
htmlwebshot/webshot.py
htmlwebshot-0.1.2.dist-info/LICENSE
htmlwebshot-0.1.2.dist-info/METADATA
htmlwebshot-0.1.2.dist-info/WHEEL
htmlwebshot-0.1.2.dist-info/top_level.txt
htmlwebshot-0.1.2.dist-info/RECORD
