Metadata-Version: 2.1
Name: htmlwebshot
Version: 0.1.2
Summary: Create Web Preview Images From url, Html-CSS ,svg, any other readable file or string.
Home-page: https://github.com/1Danish-00/htmlwebshot/
Author: 1Danish-00
Author-email: danish@ultroid.tech
License: GNU AFFERO aa rha posts GENERAL PUBLIC LICENSE (v3)
Project-URL: Bug Tracker, https://github.com/1Danish-00/htmlwebshot/issues
Keywords: screenshot,Webshot,url to image,html to image,css to image,svg to image,text to image,file to image
Platform: UNKNOWN
Classifier: Programming Language :: Python :: 3
Classifier: Programming Language :: Python :: 3.6
Classifier: Programming Language :: Python :: 3.7
Classifier: Programming Language :: Python :: 3.8
Classifier: Programming Language :: Python :: 3.9
Classifier: License :: OSI Approved :: GNU General Public License v3 (GPLv3)
Classifier: Operating System :: OS Independent
Classifier: Topic :: Text Processing
Classifier: Topic :: Text Processing :: General
Classifier: Topic :: Text Processing :: Markup
Classifier: Topic :: Text Processing :: Markup :: HTML
Classifier: Topic :: Text Processing :: Markup :: XML
Classifier: Topic :: Utilities
Requires-Python: >=3.5
License-File: LICENSE
Requires-Dist: asyncio
